trld/__init__.py
trld/__main__.py
trld/api.py
trld/builtins.py
trld/cli.py
trld/mimetypes.py
trld/py.typed
trld/rdfterms.py
trld/jsonld/__init__.py
trld/jsonld/__main__.py
trld/jsonld/base.py
trld/jsonld/compaction.py
trld/jsonld/context.py
trld/jsonld/docloader.py
trld/jsonld/expansion.py
trld/jsonld/flattening.py
trld/jsonld/invcontext.py
trld/jsonld/rdf.py
trld/jsonld/star.py
trld/jsonld/test.py
trld/jsonld/testbase.py
trld/jsonld/extras/__init__.py
trld/jsonld/extras/index.py
trld/nq/__init__.py
trld/nq/parser.py
trld/nq/serializer.py
trld/platform/__init__.py
trld/platform/common.py
trld/platform/io.py
trld/trig/__init__.py
trld/trig/parser.py
trld/trig/serializer.py
trld/trig/test.py
trld/trig/test_serializer.py
trld/tvm/__init__.py
trld/tvm/__main__.py
trld/tvm/mapmaker.py
trld/tvm/mapper.py
trld/tvm/test.py
trld-0.2.0.dist-info/LICENSE
trld-0.2.0.dist-info/METADATA
trld-0.2.0.dist-info/WHEEL
trld-0.2.0.dist-info/entry_points.txt
trld-0.2.0.dist-info/top_level.txt
trld-0.2.0.dist-info/RECORD
