Metadata-Version: 2.1
Name: trld
Version: 0.2.0
Summary: A library of algorithms for working with JSON-LD and translating between various forms of RDF.
Home-page: https://github.com/niklasl/trld
Author: Niklas Lindström
Author-email: lindstream@gmail.com
Classifier: Programming Language :: Python :: 3
Classifier: License :: OSI Approved
Classifier: Operating System :: OS Independent
Classifier: Typing :: Typed
Requires-Python: >=3.6
License-File: LICENSE
